qvalidation/__init__.py
qvalidation/rule.py
qvalidation/validation.py
qvalidation-0.2.dist-info/LICENSE
qvalidation-0.2.dist-info/METADATA
qvalidation-0.2.dist-info/WHEEL
qvalidation-0.2.dist-info/top_level.txt
qvalidation-0.2.dist-info/RECORD
