Metadata-Version: 2.1
Name: qvalidation
Version: 0.2
Summary: Simple rule validation
Home-page: https://github.com/rvettori/qvalidation
Author: Rafael Vettori
Author-email: rafael.vettori@gmail.com
License: MIT
Platform: UNKNOWN
